{
  "type": "Program",
  "start": 0,
  "end": 578,
  "loc": {
    "start": {
      "line": 1,
      "column": 0
    },
    "end": {
      "line": 23,
      "column": 36
    }
  },
  "sourceType": "module",
  "body": [
    {
      "type": "ImportDeclaration",
      "start": 0,
      "end": 40,
      "loc": {
        "start": {
          "line": 1,
          "column": 0
        },
        "end": {
          "line": 1,
          "column": 40
        }
      },
      "specifiers": [
        {
          "type": "ImportDefaultSpecifier",
          "start": 7,
          "end": 12,
          "loc": {
            "start": {
              "line": 1,
              "column": 7
            },
            "end": {
              "line": 1,
              "column": 12
            }
          },
          "local": {
            "type": "Identifier",
            "start": 7,
            "end": 12,
            "loc": {
              "start": {
                "line": 1,
                "column": 7
              },
              "end": {
                "line": 1,
                "column": 12
              }
            },
            "name": "React"
          }
        },
        {
          "type": "ImportSpecifier",
          "start": 16,
          "end": 25,
          "loc": {
            "start": {
              "line": 1,
              "column": 16
            },
            "end": {
              "line": 1,
              "column": 25
            }
          },
          "imported": {
            "type": "Identifier",
            "start": 16,
            "end": 25,
            "loc": {
              "start": {
                "line": 1,
                "column": 16
              },
              "end": {
                "line": 1,
                "column": 25
              }
            },
            "name": "Component"
          },
          "local": {
            "type": "Identifier",
            "start": 16,
            "end": 25,
            "loc": {
              "start": {
                "line": 1,
                "column": 16
              },
              "end": {
                "line": 1,
                "column": 25
              }
            },
            "name": "Component"
          }
        }
      ],
      "importKind": "value",
      "source": {
        "type": "Literal",
        "start": 33,
        "end": 40,
        "loc": {
          "start": {
            "line": 1,
            "column": 33
          },
          "end": {
            "line": 1,
            "column": 40
          }
        },
        "value": "react",
        "rawValue": "react",
        "raw": "'react'"
      }
    },
    {
      "type": "ImportDeclaration",
      "start": 41,
      "end": 74,
      "loc": {
        "start": {
          "line": 2,
          "column": 0
        },
        "end": {
          "line": 2,
          "column": 33
        }
      },
      "specifiers": [
        {
          "type": "ImportSpecifier",
          "start": 49,
          "end": 55,
          "loc": {
            "start": {
              "line": 2,
              "column": 8
            },
            "end": {
              "line": 2,
              "column": 14
            }
          },
          "imported": {
            "type": "Identifier",
            "start": 49,
            "end": 55,
            "loc": {
              "start": {
                "line": 2,
                "column": 8
              },
              "end": {
                "line": 2,
                "column": 14
              }
            },
            "name": "Button"
          },
          "local": {
            "type": "Identifier",
            "start": 49,
            "end": 55,
            "loc": {
              "start": {
                "line": 2,
                "column": 8
              },
              "end": {
                "line": 2,
                "column": 14
              }
            },
            "name": "Button"
          }
        }
      ],
      "importKind": "value",
      "source": {
        "type": "Literal",
        "start": 62,
        "end": 73,
        "loc": {
          "start": {
            "line": 2,
            "column": 21
          },
          "end": {
            "line": 2,
            "column": 32
          }
        },
        "value": "react-mdl",
        "rawValue": "react-mdl",
        "raw": "'react-mdl'"
      }
    },
    {
      "type": "ImportDeclaration",
      "start": 75,
      "end": 154,
      "loc": {
        "start": {
          "line": 3,
          "column": 0
        },
        "end": {
          "line": 3,
          "column": 79
        }
      },
      "specifiers": [
        {
          "type": "ImportSpecifier",
          "start": 84,
          "end": 90,
          "loc": {
            "start": {
              "line": 3,
              "column": 9
            },
            "end": {
              "line": 3,
              "column": 15
            }
          },
          "imported": {
            "type": "Identifier",
            "start": 84,
            "end": 90,
            "loc": {
              "start": {
                "line": 3,
                "column": 9
              },
              "end": {
                "line": 3,
                "column": 15
              }
            },
            "name": "Router"
          },
          "local": {
            "type": "Identifier",
            "start": 84,
            "end": 90,
            "loc": {
              "start": {
                "line": 3,
                "column": 9
              },
              "end": {
                "line": 3,
                "column": 15
              }
            },
            "name": "Router"
          }
        },
        {
          "type": "ImportSpecifier",
          "start": 92,
          "end": 97,
          "loc": {
            "start": {
              "line": 3,
              "column": 17
            },
            "end": {
              "line": 3,
              "column": 22
            }
          },
          "imported": {
            "type": "Identifier",
            "start": 92,
            "end": 97,
            "loc": {
              "start": {
                "line": 3,
                "column": 17
              },
              "end": {
                "line": 3,
                "column": 22
              }
            },
            "name": "Route"
          },
          "local": {
            "type": "Identifier",
            "start": 92,
            "end": 97,
            "loc": {
              "start": {
                "line": 3,
                "column": 17
              },
              "end": {
                "line": 3,
                "column": 22
              }
            },
            "name": "Route"
          }
        },
        {
          "type": "ImportSpecifier",
          "start": 99,
          "end": 103,
          "loc": {
            "start": {
              "line": 3,
              "column": 24
            },
            "end": {
              "line": 3,
              "column": 28
            }
          },
          "imported": {
            "type": "Identifier",
            "start": 99,
            "end": 103,
            "loc": {
              "start": {
                "line": 3,
                "column": 24
              },
              "end": {
                "line": 3,
                "column": 28
              }
            },
            "name": "Link"
          },
          "local": {
            "type": "Identifier",
            "start": 99,
            "end": 103,
            "loc": {
              "start": {
                "line": 3,
                "column": 24
              },
              "end": {
                "line": 3,
                "column": 28
              }
            },
            "name": "Link"
          }
        },
        {
          "type": "ImportSpecifier",
          "start": 105,
          "end": 119,
          "loc": {
            "start": {
              "line": 3,
              "column": 30
            },
            "end": {
              "line": 3,
              "column": 44
            }
          },
          "imported": {
            "type": "Identifier",
            "start": 105,
            "end": 119,
            "loc": {
              "start": {
                "line": 3,
                "column": 30
              },
              "end": {
                "line": 3,
                "column": 44
              }
            },
            "name": "browserHistory"
          },
          "local": {
            "type": "Identifier",
            "start": 105,
            "end": 119,
            "loc": {
              "start": {
                "line": 3,
                "column": 30
              },
              "end": {
                "line": 3,
                "column": 44
              }
            },
            "name": "browserHistory"
          }
        },
        {
          "type": "ImportSpecifier",
          "start": 121,
          "end": 131,
          "loc": {
            "start": {
              "line": 3,
              "column": 46
            },
            "end": {
              "line": 3,
              "column": 56
            }
          },
          "imported": {
            "type": "Identifier",
            "start": 121,
            "end": 131,
            "loc": {
              "start": {
                "line": 3,
                "column": 46
              },
              "end": {
                "line": 3,
                "column": 56
              }
            },
            "name": "IndexRoute"
          },
          "local": {
            "type": "Identifier",
            "start": 121,
            "end": 131,
            "loc": {
              "start": {
                "line": 3,
                "column": 46
              },
              "end": {
                "line": 3,
                "column": 56
              }
            },
            "name": "IndexRoute"
          }
        }
      ],
      "importKind": "value",
      "source": {
        "type": "Literal",
        "start": 140,
        "end": 154,
        "loc": {
          "start": {
            "line": 3,
            "column": 65
          },
          "end": {
            "line": 3,
            "column": 79
          }
        },
        "value": "react-router",
        "rawValue": "react-router",
        "raw": "'react-router'"
      }
    },
    {
      "type": "VariableDeclaration",
      "start": 156,
      "end": 243,
      "loc": {
        "start": {
          "line": 5,
          "column": 0
        },
        "end": {
          "line": 9,
          "column": 1
        }
      },
      "declarations": [
        {
          "type": "VariableDeclarator",
          "start": 160,
          "end": 243,
          "loc": {
            "start": {
              "line": 5,
              "column": 4
            },
            "end": {
              "line": 9,
              "column": 1
            }
          },
          "id": {
            "type": "Identifier",
            "start": 160,
            "end": 168,
            "loc": {
              "start": {
                "line": 5,
                "column": 4
              },
              "end": {
                "line": 5,
                "column": 12
              }
            },
            "name": "divStyle"
          },
          "init": {
            "type": "ObjectExpression",
            "start": 171,
            "end": 243,
            "loc": {
              "start": {
                "line": 5,
                "column": 15
              },
              "end": {
                "line": 9,
                "column": 1
              }
            },
            "properties": [
              {
                "type": "Property",
                "start": 177,
                "end": 185,
                "loc": {
                  "start": {
                    "line": 6,
                    "column": 4
                  },
                  "end": {
                    "line": 6,
                    "column": 12
                  }
                },
                "method": false,
                "shorthand": false,
                "computed": false,
                "key": {
                  "type": "Identifier",
                  "start": 177,
                  "end": 182,
                  "loc": {
                    "start": {
                      "line": 6,
                      "column": 4
                    },
                    "end": {
                      "line": 6,
                      "column": 9
                    }
                  },
                  "name": "order"
                },
                "value": {
                  "type": "Literal",
                  "start": 184,
                  "end": 185,
                  "loc": {
                    "start": {
                      "line": 6,
                      "column": 11
                    },
                    "end": {
                      "line": 6,
                      "column": 12
                    }
                  },
                  "value": 3,
                  "rawValue": 3,
                  "raw": "3"
                },
                "kind": "init"
              },
              {
                "type": "Property",
                "start": 191,
                "end": 214,
                "loc": {
                  "start": {
                    "line": 7,
                    "column": 4
                  },
                  "end": {
                    "line": 7,
                    "column": 27
                  }
                },
                "method": false,
                "shorthand": false,
                "computed": false,
                "key": {
                  "type": "Identifier",
                  "start": 191,
                  "end": 207,
                  "loc": {
                    "start": {
                      "line": 7,
                      "column": 4
                    },
                    "end": {
                      "line": 7,
                      "column": 20
                    }
                  },
                  "name": "WebkitTransition"
                },
                "value": {
                  "type": "Literal",
                  "start": 209,
                  "end": 214,
                  "loc": {
                    "start": {
                      "line": 7,
                      "column": 22
                    },
                    "end": {
                      "line": 7,
                      "column": 27
                    }
                  },
                  "value": "all",
                  "rawValue": "all",
                  "raw": "'all'"
                },
                "kind": "init"
              },
              {
                "type": "Property",
                "start": 221,
                "end": 240,
                "loc": {
                  "start": {
                    "line": 8,
                    "column": 4
                  },
                  "end": {
                    "line": 8,
                    "column": 23
                  }
                },
                "method": false,
                "shorthand": false,
                "computed": false,
                "key": {
                  "type": "Identifier",
                  "start": 221,
                  "end": 233,
                  "loc": {
                    "start": {
                      "line": 8,
                      "column": 4
                    },
                    "end": {
                      "line": 8,
                      "column": 16
                    }
                  },
                  "name": "msTransition"
                },
                "value": {
                  "type": "Literal",
                  "start": 235,
                  "end": 240,
                  "loc": {
                    "start": {
                      "line": 8,
                      "column": 18
                    },
                    "end": {
                      "line": 8,
                      "column": 23
                    }
                  },
                  "value": "all",
                  "rawValue": "all",
                  "raw": "'all'"
                },
                "kind": "init"
              }
            ]
          }
        }
      ],
      "kind": "var"
    },
    {
      "type": "Identifier",
      "start": 245,
      "end": 538,
      "loc": {
        "start": {
          "line": 11,
          "column": 0
        },
        "end": {
          "line": 20,
          "column": 1
        }
      },
      "id": {
        "type": "Identifier",
        "start": 251,
        "end": 272,
        "loc": {
          "start": {
            "line": 11,
            "column": 6
          },
          "end": {
            "line": 11,
            "column": 27
          }
        },
        "name": "ButtonSignUpPurchaser"
      },
      "superClass": {
        "type": "Identifier",
        "start": 281,
        "end": 290,
        "loc": {
          "start": {
            "line": 11,
            "column": 36
          },
          "end": {
            "line": 11,
            "column": 45
          }
        },
        "name": "Component"
      },
      "body": {
        "type": "ClassBody",
        "start": 291,
        "end": 538,
        "loc": {
          "start": {
            "line": 11,
            "column": 46
          },
          "end": {
            "line": 20,
            "column": 1
          }
        },
        "body": [
          {
            "type": "MethodDefinition",
            "start": 297,
            "end": 536,
            "loc": {
              "start": {
                "line": 12,
                "column": 4
              },
              "end": {
                "line": 19,
                "column": 11
              }
            },
            "computed": false,
            "key": {
              "type": "Identifier",
              "start": 297,
              "end": 303,
              "loc": {
                "start": {
                  "line": 12,
                  "column": 4
                },
                "end": {
                  "line": 12,
                  "column": 10
                }
              },
              "name": "render"
            },
            "static": false,
            "kind": "method",
            "value": {
              "type": "FunctionExpression",
              "start": 303,
              "end": 536,
              "loc": {
                "start": {
                  "line": 12,
                  "column": 10
                },
                "end": {
                  "line": 19,
                  "column": 11
                }
              },
              "id": null,
              "generator": false,
              "expression": false,
              "async": false,
              "params": [],
              "body": {
                "type": "BlockStatement",
                "start": 305,
                "end": 536,
                "loc": {
                  "start": {
                    "line": 12,
                    "column": 12
                  },
                  "end": {
                    "line": 19,
                    "column": 11
                  }
                },
                "body": [
                  {
                    "type": "ReturnStatement",
                    "start": 315,
                    "end": 535,
                    "loc": {
                      "start": {
                        "line": 13,
                        "column": 8
                      },
                      "end": {
                        "line": 19,
                        "column": 10
                      }
                    },
                    "argument": {
                      "type": "JSXElement",
                      "start": 333,
                      "end": 524,
                      "loc": {
                        "start": {
                          "line": 14,
                          "column": 10
                        },
                        "end": {
                          "line": 18,
                          "column": 18
                        }
                      },
                      "openingElement": {
                        "type": "JSXOpeningElement",
                        "start": 333,
                        "end": 358,
                        "loc": {
                          "start": {
                            "line": 14,
                            "column": 10
                          },
                          "end": {
                            "line": 14,
                            "column": 35
                          }
                        },
                        "attributes": [
                          {
                            "type": "JSXAttribute",
                            "start": 339,
                            "end": 357,
                            "loc": {
                              "start": {
                                "line": 14,
                                "column": 16
                              },
                              "end": {
                                "line": 14,
                                "column": 34
                              }
                            },
                            "name": {
                              "type": "JSXIdentifier",
                              "start": 339,
                              "end": 341,
                              "loc": {
                                "start": {
                                  "line": 14,
                                  "column": 16
                                },
                                "end": {
                                  "line": 14,
                                  "column": 18
                                }
                              },
                              "name": "to"
                            },
                            "value": {
                              "type": "JSXExpressionContainer",
                              "start": 342,
                              "end": 357,
                              "loc": {
                                "start": {
                                  "line": 14,
                                  "column": 19
                                },
                                "end": {
                                  "line": 14,
                                  "column": 34
                                }
                              },
                              "expression": {
                                "type": "MemberExpression",
                                "start": 343,
                                "end": 356,
                                "loc": {
                                  "start": {
                                    "line": 14,
                                    "column": 20
                                  },
                                  "end": {
                                    "line": 14,
                                    "column": 33
                                  }
                                },
                                "object": {
                                  "type": "MemberExpression",
                                  "start": 343,
                                  "end": 353,
                                  "loc": {
                                    "start": {
                                      "line": 14,
                                      "column": 20
                                    },
                                    "end": {
                                      "line": 14,
                                      "column": 30
                                    }
                                  },
                                  "object": {
                                    "type": "ThisExpression",
                                    "start": 343,
                                    "end": 347,
                                    "loc": {
                                      "start": {
                                        "line": 14,
                                        "column": 20
                                      },
                                      "end": {
                                        "line": 14,
                                        "column": 24
                                      }
                                    }
                                  },
                                  "property": {
                                    "type": "Identifier",
                                    "start": 348,
                                    "end": 353,
                                    "loc": {
                                      "start": {
                                        "line": 14,
                                        "column": 25
                                      },
                                      "end": {
                                        "line": 14,
                                        "column": 30
                                      }
                                    },
                                    "name": "props"
                                  },
                                  "computed": false
                                },
                                "property": {
                                  "type": "Identifier",
                                  "start": 354,
                                  "end": 356,
                                  "loc": {
                                    "start": {
                                      "line": 14,
                                      "column": 31
                                    },
                                    "end": {
                                      "line": 14,
                                      "column": 33
                                    }
                                  },
                                  "name": "to"
                                },
                                "computed": false
                              }
                            }
                          }
                        ],
                        "name": {
                          "type": "JSXIdentifier",
                          "start": 334,
                          "end": 338,
                          "loc": {
                            "start": {
                              "line": 14,
                              "column": 11
                            },
                            "end": {
                              "line": 14,
                              "column": 15
                            }
                          },
                          "name": "Link"
                        },
                        "selfClosing": false
                      },
                      "closingElement": {
                        "type": "JSXClosingElement",
                        "start": 517,
                        "end": 524,
                        "loc": {
                          "start": {
                            "line": 18,
                            "column": 11
                          },
                          "end": {
                            "line": 18,
                            "column": 18
                          }
                        },
                        "name": {
                          "type": "JSXIdentifier",
                          "start": 519,
                          "end": 523,
                          "loc": {
                            "start": {
                              "line": 18,
                              "column": 13
                            },
                            "end": {
                              "line": 18,
                              "column": 17
                            }
                          },
                          "name": "Link"
                        }
                      },
                      "children": [
                        {
                          "type": "Literal",
                          "start": 358,
                          "end": 373,
                          "loc": {
                            "start": {
                              "line": 14,
                              "column": 35
                            },
                            "end": {
                              "line": 15,
                              "column": 14
                            }
                          },
                          "value": "\n              ",
                          "rawValue": null,
                          "raw": "\n              "
                        },
                        {
                          "type": "JSXElement",
                          "start": 373,
                          "end": 505,
                          "loc": {
                            "start": {
                              "line": 15,
                              "column": 14
                            },
                            "end": {
                              "line": 17,
                              "column": 23
                            }
                          },
                          "openingElement": {
                            "type": "JSXOpeningElement",
                            "start": 373,
                            "end": 455,
                            "loc": {
                              "start": {
                                "line": 15,
                                "column": 14
                              },
                              "end": {
                                "line": 15,
                                "column": 96
                              }
                            },
                            "attributes": [
                              {
                                "type": "JSXAttribute",
                                "start": 381,
                                "end": 387,
                                "loc": {
                                  "start": {
                                    "line": 15,
                                    "column": 22
                                  },
                                  "end": {
                                    "line": 15,
                                    "column": 28
                                  }
                                },
                                "name": {
                                  "type": "JSXIdentifier",
                                  "start": 381,
                                  "end": 387,
                                  "loc": {
                                    "start": {
                                      "line": 15,
                                      "column": 22
                                    },
                                    "end": {
                                      "line": 15,
                                      "column": 28
                                    }
                                  },
                                  "name": "raised"
                                },
                                "value": null
                              },
                              {
                                "type": "JSXAttribute",
                                "start": 388,
                                "end": 394,
                                "loc": {
                                  "start": {
                                    "line": 15,
                                    "column": 29
                                  },
                                  "end": {
                                    "line": 15,
                                    "column": 35
                                  }
                                },
                                "name": {
                                  "type": "JSXIdentifier",
                                  "start": 388,
                                  "end": 394,
                                  "loc": {
                                    "start": {
                                      "line": 15,
                                      "column": 29
                                    },
                                    "end": {
                                      "line": 15,
                                      "column": 35
                                    }
                                  },
                                  "name": "ripple"
                                },
                                "value": null
                              },
                              {
                                "type": "JSXAttribute",
                                "start": 395,
                                "end": 401,
                                "loc": {
                                  "start": {
                                    "line": 15,
                                    "column": 36
                                  },
                                  "end": {
                                    "line": 15,
                                    "column": 42
                                  }
                                },
                                "name": {
                                  "type": "JSXIdentifier",
                                  "start": 395,
                                  "end": 401,
                                  "loc": {
                                    "start": {
                                      "line": 15,
                                      "column": 36
                                    },
                                    "end": {
                                      "line": 15,
                                      "column": 42
                                    }
                                  },
                                  "name": "accent"
                                },
                                "value": null
                              },
                              {
                                "type": "JSXAttribute",
                                "start": 402,
                                "end": 453,
                                "loc": {
                                  "start": {
                                    "line": 15,
                                    "column": 43
                                  },
                                  "end": {
                                    "line": 15,
                                    "column": 94
                                  }
                                },
                                "name": {
                                  "type": "JSXIdentifier",
                                  "start": 402,
                                  "end": 411,
                                  "loc": {
                                    "start": {
                                      "line": 15,
                                      "column": 43
                                    },
                                    "end": {
                                      "line": 15,
                                      "column": 52
                                    }
                                  },
                                  "name": "className"
                                },
                                "value": {
                                  "type": "Literal",
                                  "start": 412,
                                  "end": 453,
                                  "loc": {
                                    "start": {
                                      "line": 15,
                                      "column": 53
                                    },
                                    "end": {
                                      "line": 15,
                                      "column": 94
                                    }
                                  },
                                  "value": "mdl-color--indigo mdl-color-text--white",
                                  "rawValue": null,
                                  "raw": "\"mdl-color--indigo mdl-color-text--white\""
                                }
                              }
                            ],
                            "name": {
                              "type": "JSXIdentifier",
                              "start": 374,
                              "end": 380,
                              "loc": {
                                "start": {
                                  "line": 15,
                                  "column": 15
                                },
                                "end": {
                                  "line": 15,
                                  "column": 21
                                }
                              },
                              "name": "Button"
                            },
                            "selfClosing": false
                          },
                          "closingElement": {
                            "type": "JSXClosingElement",
                            "start": 496,
                            "end": 505,
                            "loc": {
                              "start": {
                                "line": 17,
                                "column": 14
                              },
                              "end": {
                                "line": 17,
                                "column": 23
                              }
                            },
                            "name": {
                              "type": "JSXIdentifier",
                              "start": 498,
                              "end": 504,
                              "loc": {
                                "start": {
                                  "line": 17,
                                  "column": 16
                                },
                                "end": {
                                  "line": 17,
                                  "column": 22
                                }
                              },
                              "name": "Button"
                            }
                          },
                          "children": [
                            {
                              "type": "Literal",
                              "start": 455,
                              "end": 496,
                              "loc": {
                                "start": {
                                  "line": 15,
                                  "column": 96
                                },
                                "end": {
                                  "line": 17,
                                  "column": 14
                                }
                              },
                              "value": "\n                Purchaser\n              ",
                              "rawValue": null,
                              "raw": "\n                Purchaser\n              "
                            }
                          ]
                        },
                        {
                          "type": "Literal",
                          "start": 505,
                          "end": 517,
                          "loc": {
                            "start": {
                              "line": 17,
                              "column": 23
                            },
                            "end": {
                              "line": 18,
                              "column": 11
                            }
                          },
                          "value": "\n           ",
                          "rawValue": null,
                          "raw": "\n           "
                        }
                      ],
                      "parenthesizedExpression": true
                    }
                  }
                ]
              }
            }
          }
        ]
      },
      "name": "_",
      "leadingComments": [],
      "trailingComments": []
    },
    {
      "type": "EmptyStatement",
      "start": 538,
      "end": 539,
      "loc": {
        "start": {
          "line": 20,
          "column": 1
        },
        "end": {
          "line": 20,
          "column": 2
        }
      }
    },
    {
      "type": "Identifier",
      "start": 542,
      "end": 578,
      "loc": {
        "start": {
          "line": 23,
          "column": 0
        },
        "end": {
          "line": 23,
          "column": 36
        }
      },
      "declaration": {
        "type": "Identifier",
        "start": 557,
        "end": 578,
        "loc": {
          "start": {
            "line": 23,
            "column": 15
          },
          "end": {
            "line": 23,
            "column": 36
          }
        },
        "name": "ButtonSignUpPurchaser"
      },
      "name": "_",
      "leadingComments": [],
      "trailingComments": []
    },
    {
      "type": "ExportDefaultDeclaration",
      "start": 542,
      "end": 578,
      "loc": {
        "start": {
          "line": 23,
          "column": 0
        },
        "end": {
          "line": 23,
          "column": 36
        }
      },
      "declaration": {
        "type": "ClassDeclaration",
        "start": 245,
        "end": 538,
        "loc": {
          "start": {
            "line": 11,
            "column": 0
          },
          "end": {
            "line": 20,
            "column": 1
          }
        },
        "id": {
          "type": "Identifier",
          "start": 251,
          "end": 272,
          "loc": {
            "start": {
              "line": 11,
              "column": 6
            },
            "end": {
              "line": 11,
              "column": 27
            }
          },
          "name": "ButtonSignUpPurchaser"
        },
        "superClass": {
          "type": "Identifier",
          "start": 281,
          "end": 290,
          "loc": {
            "start": {
              "line": 11,
              "column": 36
            },
            "end": {
              "line": 11,
              "column": 45
            }
          },
          "name": "Component"
        },
        "body": {
          "type": "ClassBody",
          "start": 291,
          "end": 538,
          "loc": {
            "start": {
              "line": 11,
              "column": 46
            },
            "end": {
              "line": 20,
              "column": 1
            }
          },
          "body": [
            {
              "type": "MethodDefinition",
              "start": 297,
              "end": 536,
              "loc": {
                "start": {
                  "line": 12,
                  "column": 4
                },
                "end": {
                  "line": 19,
                  "column": 11
                }
              },
              "computed": false,
              "key": {
                "type": "Identifier",
                "start": 297,
                "end": 303,
                "loc": {
                  "start": {
                    "line": 12,
                    "column": 4
                  },
                  "end": {
                    "line": 12,
                    "column": 10
                  }
                },
                "name": "render"
              },
              "static": false,
              "kind": "method",
              "value": {
                "type": "FunctionExpression",
                "start": 303,
                "end": 536,
                "loc": {
                  "start": {
                    "line": 12,
                    "column": 10
                  },
                  "end": {
                    "line": 19,
                    "column": 11
                  }
                },
                "id": null,
                "generator": false,
                "expression": false,
                "async": false,
                "params": [],
                "body": {
                  "type": "BlockStatement",
                  "start": 305,
                  "end": 536,
                  "loc": {
                    "start": {
                      "line": 12,
                      "column": 12
                    },
                    "end": {
                      "line": 19,
                      "column": 11
                    }
                  },
                  "body": [
                    {
                      "type": "ReturnStatement",
                      "start": 315,
                      "end": 535,
                      "loc": {
                        "start": {
                          "line": 13,
                          "column": 8
                        },
                        "end": {
                          "line": 19,
                          "column": 10
                        }
                      },
                      "argument": {
                        "type": "JSXElement",
                        "start": 333,
                        "end": 524,
                        "loc": {
                          "start": {
                            "line": 14,
                            "column": 10
                          },
                          "end": {
                            "line": 18,
                            "column": 18
                          }
                        },
                        "openingElement": {
                          "type": "JSXOpeningElement",
                          "start": 333,
                          "end": 358,
                          "loc": {
                            "start": {
                              "line": 14,
                              "column": 10
                            },
                            "end": {
                              "line": 14,
                              "column": 35
                            }
                          },
                          "attributes": [
                            {
                              "type": "JSXAttribute",
                              "start": 339,
                              "end": 357,
                              "loc": {
                                "start": {
                                  "line": 14,
                                  "column": 16
                                },
                                "end": {
                                  "line": 14,
                                  "column": 34
                                }
                              },
                              "name": {
                                "type": "JSXIdentifier",
                                "start": 339,
                                "end": 341,
                                "loc": {
                                  "start": {
                                    "line": 14,
                                    "column": 16
                                  },
                                  "end": {
                                    "line": 14,
                                    "column": 18
                                  }
                                },
                                "name": "to"
                              },
                              "value": {
                                "type": "JSXExpressionContainer",
                                "start": 342,
                                "end": 357,
                                "loc": {
                                  "start": {
                                    "line": 14,
                                    "column": 19
                                  },
                                  "end": {
                                    "line": 14,
                                    "column": 34
                                  }
                                },
                                "expression": {
                                  "type": "MemberExpression",
                                  "start": 343,
                                  "end": 356,
                                  "loc": {
                                    "start": {
                                      "line": 14,
                                      "column": 20
                                    },
                                    "end": {
                                      "line": 14,
                                      "column": 33
                                    }
                                  },
                                  "object": {
                                    "type": "MemberExpression",
                                    "start": 343,
                                    "end": 353,
                                    "loc": {
                                      "start": {
                                        "line": 14,
                                        "column": 20
                                      },
                                      "end": {
                                        "line": 14,
                                        "column": 30
                                      }
                                    },
                                    "object": {
                                      "type": "ThisExpression",
                                      "start": 343,
                                      "end": 347,
                                      "loc": {
                                        "start": {
                                          "line": 14,
                                          "column": 20
                                        },
                                        "end": {
                                          "line": 14,
                                          "column": 24
                                        }
                                      }
                                    },
                                    "property": {
                                      "type": "Identifier",
                                      "start": 348,
                                      "end": 353,
                                      "loc": {
                                        "start": {
                                          "line": 14,
                                          "column": 25
                                        },
                                        "end": {
                                          "line": 14,
                                          "column": 30
                                        }
                                      },
                                      "name": "props"
                                    },
                                    "computed": false
                                  },
                                  "property": {
                                    "type": "Identifier",
                                    "start": 354,
                                    "end": 356,
                                    "loc": {
                                      "start": {
                                        "line": 14,
                                        "column": 31
                                      },
                                      "end": {
                                        "line": 14,
                                        "column": 33
                                      }
                                    },
                                    "name": "to"
                                  },
                                  "computed": false
                                }
                              }
                            }
                          ],
                          "name": {
                            "type": "JSXIdentifier",
                            "start": 334,
                            "end": 338,
                            "loc": {
                              "start": {
                                "line": 14,
                                "column": 11
                              },
                              "end": {
                                "line": 14,
                                "column": 15
                              }
                            },
                            "name": "Link"
                          },
                          "selfClosing": false
                        },
                        "closingElement": {
                          "type": "JSXClosingElement",
                          "start": 517,
                          "end": 524,
                          "loc": {
                            "start": {
                              "line": 18,
                              "column": 11
                            },
                            "end": {
                              "line": 18,
                              "column": 18
                            }
                          },
                          "name": {
                            "type": "JSXIdentifier",
                            "start": 519,
                            "end": 523,
                            "loc": {
                              "start": {
                                "line": 18,
                                "column": 13
                              },
                              "end": {
                                "line": 18,
                                "column": 17
                              }
                            },
                            "name": "Link"
                          }
                        },
                        "children": [
                          {
                            "type": "Literal",
                            "start": 358,
                            "end": 373,
                            "loc": {
                              "start": {
                                "line": 14,
                                "column": 35
                              },
                              "end": {
                                "line": 15,
                                "column": 14
                              }
                            },
                            "value": "\n              ",
                            "rawValue": null,
                            "raw": "\n              "
                          },
                          {
                            "type": "JSXElement",
                            "start": 373,
                            "end": 505,
                            "loc": {
                              "start": {
                                "line": 15,
                                "column": 14
                              },
                              "end": {
                                "line": 17,
                                "column": 23
                              }
                            },
                            "openingElement": {
                              "type": "JSXOpeningElement",
                              "start": 373,
                              "end": 455,
                              "loc": {
                                "start": {
                                  "line": 15,
                                  "column": 14
                                },
                                "end": {
                                  "line": 15,
                                  "column": 96
                                }
                              },
                              "attributes": [
                                {
                                  "type": "JSXAttribute",
                                  "start": 381,
                                  "end": 387,
                                  "loc": {
                                    "start": {
                                      "line": 15,
                                      "column": 22
                                    },
                                    "end": {
                                      "line": 15,
                                      "column": 28
                                    }
                                  },
                                  "name": {
                                    "type": "JSXIdentifier",
                                    "start": 381,
                                    "end": 387,
                                    "loc": {
                                      "start": {
                                        "line": 15,
                                        "column": 22
                                      },
                                      "end": {
                                        "line": 15,
                                        "column": 28
                                      }
                                    },
                                    "name": "raised"
                                  },
                                  "value": null
                                },
                                {
                                  "type": "JSXAttribute",
                                  "start": 388,
                                  "end": 394,
                                  "loc": {
                                    "start": {
                                      "line": 15,
                                      "column": 29
                                    },
                                    "end": {
                                      "line": 15,
                                      "column": 35
                                    }
                                  },
                                  "name": {
                                    "type": "JSXIdentifier",
                                    "start": 388,
                                    "end": 394,
                                    "loc": {
                                      "start": {
                                        "line": 15,
                                        "column": 29
                                      },
                                      "end": {
                                        "line": 15,
                                        "column": 35
                                      }
                                    },
                                    "name": "ripple"
                                  },
                                  "value": null
                                },
                                {
                                  "type": "JSXAttribute",
                                  "start": 395,
                                  "end": 401,
                                  "loc": {
                                    "start": {
                                      "line": 15,
                                      "column": 36
                                    },
                                    "end": {
                                      "line": 15,
                                      "column": 42
                                    }
                                  },
                                  "name": {
                                    "type": "JSXIdentifier",
                                    "start": 395,
                                    "end": 401,
                                    "loc": {
                                      "start": {
                                        "line": 15,
                                        "column": 36
                                      },
                                      "end": {
                                        "line": 15,
                                        "column": 42
                                      }
                                    },
                                    "name": "accent"
                                  },
                                  "value": null
                                },
                                {
                                  "type": "JSXAttribute",
                                  "start": 402,
                                  "end": 453,
                                  "loc": {
                                    "start": {
                                      "line": 15,
                                      "column": 43
                                    },
                                    "end": {
                                      "line": 15,
                                      "column": 94
                                    }
                                  },
                                  "name": {
                                    "type": "JSXIdentifier",
                                    "start": 402,
                                    "end": 411,
                                    "loc": {
                                      "start": {
                                        "line": 15,
                                        "column": 43
                                      },
                                      "end": {
                                        "line": 15,
                                        "column": 52
                                      }
                                    },
                                    "name": "className"
                                  },
                                  "value": {
                                    "type": "Literal",
                                    "start": 412,
                                    "end": 453,
                                    "loc": {
                                      "start": {
                                        "line": 15,
                                        "column": 53
                                      },
                                      "end": {
                                        "line": 15,
                                        "column": 94
                                      }
                                    },
                                    "value": "mdl-color--indigo mdl-color-text--white",
                                    "rawValue": null,
                                    "raw": "\"mdl-color--indigo mdl-color-text--white\""
                                  }
                                }
                              ],
                              "name": {
                                "type": "JSXIdentifier",
                                "start": 374,
                                "end": 380,
                                "loc": {
                                  "start": {
                                    "line": 15,
                                    "column": 15
                                  },
                                  "end": {
                                    "line": 15,
                                    "column": 21
                                  }
                                },
                                "name": "Button"
                              },
                              "selfClosing": false
                            },
                            "closingElement": {
                              "type": "JSXClosingElement",
                              "start": 496,
                              "end": 505,
                              "loc": {
                                "start": {
                                  "line": 17,
                                  "column": 14
                                },
                                "end": {
                                  "line": 17,
                                  "column": 23
                                }
                              },
                              "name": {
                                "type": "JSXIdentifier",
                                "start": 498,
                                "end": 504,
                                "loc": {
                                  "start": {
                                    "line": 17,
                                    "column": 16
                                  },
                                  "end": {
                                    "line": 17,
                                    "column": 22
                                  }
                                },
                                "name": "Button"
                              }
                            },
                            "children": [
                              {
                                "type": "Literal",
                                "start": 455,
                                "end": 496,
                                "loc": {
                                  "start": {
                                    "line": 15,
                                    "column": 96
                                  },
                                  "end": {
                                    "line": 17,
                                    "column": 14
                                  }
                                },
                                "value": "\n                Purchaser\n              ",
                                "rawValue": null,
                                "raw": "\n                Purchaser\n              "
                              }
                            ]
                          },
                          {
                            "type": "Literal",
                            "start": 505,
                            "end": 517,
                            "loc": {
                              "start": {
                                "line": 17,
                                "column": 23
                              },
                              "end": {
                                "line": 18,
                                "column": 11
                              }
                            },
                            "value": "\n           ",
                            "rawValue": null,
                            "raw": "\n           "
                          }
                        ],
                        "parenthesizedExpression": true
                      }
                    }
                  ]
                }
              }
            }
          ]
        },
        "__esdoc__pseudo_export": false,
        "leadingComments": [],
        "trailingComments": []
      },
      "leadingComments": null
    }
  ]
}